django_adal/MSAdalAuth.py
django_adal/__init__.py
django_adal/models.py
django_adal/msgraph.py
django_adal/urls.py
django_adal/views.py
django_adal-0.1.dist-info/DESCRIPTION.rst
django_adal-0.1.dist-info/METADATA
django_adal-0.1.dist-info/RECORD
django_adal-0.1.dist-info/WHEEL
django_adal-0.1.dist-info/metadata.json
django_adal-0.1.dist-info/top_level.txt
